randname/__init__.py
randname/__main__.py
randname/config.py
randname/core.py
randname/data/ES/first_names/2020_M
randname/data/ES/info.json
randname/data/ES/last_names/2020_N
randname/data/PL/first_names/2021_F
randname/data/PL/first_names/2021_M
randname/data/PL/info.json
randname/data/PL/last_names/2020_F
randname/data/PL/last_names/2020_M
randname/data/US/first_names/2018_F
randname/data/US/first_names/2018_M
randname/data/US/info.json
randname/data/US/last_names/2010_N
randname/database.py
randname/error.py
randname/py.typed
rname-1.0.0.dist-info/WHEEL
rname-1.0.0.dist-info/METADATA
rname-1.0.0.dist-info/RECORD
