Metadata-Version: 2.3
Name: rname
Version: 1.0.0
Summary: Get random first/last name
Keywords: python,rand,name,randname
Author: Adam Walkiewicz
Author-email: Adam Walkiewicz <aj.walkiewicz@gmail.com>
Classifier: Development Status :: 4 - Beta
Classifier: License :: OSI Approved :: MIT License
Classifier: Operating System :: OS Independent
Classifier: Programming Language :: Python :: 3.12
Classifier: Programming Language :: Python :: 3.13
Classifier: Programming Language :: Python :: 3.14
Requires-Dist: jsonschema>=4.25.1
Requires-Python: >=3.12
Project-URL: Documentation, https://ajwalkiewicz.github.io/randname
Project-URL: Issues, https://github.com/ajwalkiewicz/randname/issues
Project-URL: Repository, https://github.com/ajwalkiewicz/randname
